<annotation>
	<folder>Sixray annotation 500</folder>
	<filename>P00456.jpg</filename>
	<path>D:\Users\Joseph.ROSE-WS3A\Desktop\labelImg\data\Sixray annotation 500\P00456.jpg</path>
	<source>
		<database>Unknown</database>
	</source>
	<size>
		<width>814</width>
		<height>735</height>
		<depth>3</depth>
	</size>
	<segmented>0</segmented>
	<object>
		<name>wrench</name>
		<pose>Unspecified</pose>
		<truncated>0</truncated>
		<difficult>0</difficult>
		<bndbox>
			<xmin>126</xmin>
			<ymin>287</ymin>
			<xmax>307</xmax>
			<ymax>611</ymax>
		</bndbox>
	</object>
	<object>
		<name>wrench</name>
		<pose>Unspecified</pose>
		<truncated>0</truncated>
		<difficult>0</difficult>
		<bndbox>
			<xmin>159</xmin>
			<ymin>264</ymin>
			<xmax>368</xmax>
			<ymax>289</ymax>
		</bndbox>
	</object>
	<object>
		<name>wrench</name>
		<pose>Unspecified</pose>
		<truncated>0</truncated>
		<difficult>0</difficult>
		<bndbox>
			<xmin>367</xmin>
			<ymin>138</ymin>
			<xmax>505</xmax>
			<ymax>336</ymax>
		</bndbox>
	</object>
	<object>
		<name>gun</name>
		<pose>Unspecified</pose>
		<truncated>0</truncated>
		<difficult>0</difficult>
		<bndbox>
			<xmin>435</xmin>
			<ymin>205</ymin>
			<xmax>529</xmax>
			<ymax>320</ymax>
		</bndbox>
	</object>
	<object>
		<name>gun</name>
		<pose>Unspecified</pose>
		<truncated>0</truncated>
		<difficult>0</difficult>
		<bndbox>
			<xmin>148</xmin>
			<ymin>421</ymin>
			<xmax>278</xmax>
			<ymax>553</ymax>
		</bndbox>
	</object>
	<object>
		<name>knife</name>
		<pose>Unspecified</pose>
		<truncated>0</truncated>
		<difficult>0</difficult>
		<bndbox>
			<xmin>421</xmin>
			<ymin>102</ymin>
			<xmax>521</xmax>
			<ymax>349</ymax>
		</bndbox>
	</object>
</annotation>
