<annotation>
	<folder>Sixray annotation 500</folder>
	<filename>P01408.jpg</filename>
	<path>D:\Users\Joseph.ROSE-WS3A\Desktop\labelImg\data\Sixray annotation 500\P01408.jpg</path>
	<source>
		<database>Unknown</database>
	</source>
	<size>
		<width>583</width>
		<height>660</height>
		<depth>3</depth>
	</size>
	<segmented>0</segmented>
	<object>
		<name>gun</name>
		<pose>Unspecified</pose>
		<truncated>0</truncated>
		<difficult>0</difficult>
		<bndbox>
			<xmin>435</xmin>
			<ymin>227</ymin>
			<xmax>551</xmax>
			<ymax>379</ymax>
		</bndbox>
	</object>
	<object>
		<name>gun</name>
		<pose>Unspecified</pose>
		<truncated>0</truncated>
		<difficult>0</difficult>
		<bndbox>
			<xmin>259</xmin>
			<ymin>266</ymin>
			<xmax>353</xmax>
			<ymax>422</ymax>
		</bndbox>
	</object>
</annotation>
