<annotation>
	<folder>Sixray annotation 500</folder>
	<filename>P01755.jpg</filename>
	<path>D:\Users\Joseph.ROSE-WS3A\Desktop\labelImg\data\Sixray annotation 500\P01755.jpg</path>
	<source>
		<database>Unknown</database>
	</source>
	<size>
		<width>541</width>
		<height>620</height>
		<depth>3</depth>
	</size>
	<segmented>0</segmented>
	<object>
		<name>gun</name>
		<pose>Unspecified</pose>
		<truncated>0</truncated>
		<difficult>0</difficult>
		<bndbox>
			<xmin>262</xmin>
			<ymin>234</ymin>
			<xmax>393</xmax>
			<ymax>365</ymax>
		</bndbox>
	</object>
	<object>
		<name>gun</name>
		<pose>Unspecified</pose>
		<truncated>0</truncated>
		<difficult>0</difficult>
		<bndbox>
			<xmin>257</xmin>
			<ymin>273</ymin>
			<xmax>438</xmax>
			<ymax>418</ymax>
		</bndbox>
	</object>
</annotation>
