<annotation>
	<folder>Sixray less than 500</folder>
	<filename>P02549.jpg</filename>
	<path>D:\Users\Joseph.ROSE-WS3A\Desktop\Sixray less than 500\P02549.jpg</path>
	<source>
		<database>Unknown</database>
	</source>
	<size>
		<width>1303</width>
		<height>434</height>
		<depth>3</depth>
	</size>
	<segmented>0</segmented>
	<object>
		<name>gun</name>
		<pose>Unspecified</pose>
		<truncated>0</truncated>
		<difficult>0</difficult>
		<bndbox>
			<xmin>519</xmin>
			<ymin>181</ymin>
			<xmax>664</xmax>
			<ymax>308</ymax>
		</bndbox>
	</object>
</annotation>
