<annotation>
	<folder>Sixray annotation 500</folder>
	<filename>P02994.jpg</filename>
	<path>D:\Users\Joseph.ROSE-WS3A\Desktop\labelImg\data\Sixray annotation 500\P02994.jpg</path>
	<source>
		<database>Unknown</database>
	</source>
	<size>
		<width>822</width>
		<height>509</height>
		<depth>3</depth>
	</size>
	<segmented>0</segmented>
	<object>
		<name>gun</name>
		<pose>Unspecified</pose>
		<truncated>0</truncated>
		<difficult>0</difficult>
		<bndbox>
			<xmin>334</xmin>
			<ymin>391</ymin>
			<xmax>481</xmax>
			<ymax>463</ymax>
		</bndbox>
	</object>
</annotation>
