<annotation>
	<folder>Sixray annotation 500</folder>
	<filename>P03052.jpg</filename>
	<path>D:\Users\Joseph.ROSE-WS3A\Desktop\labelImg\data\Sixray annotation 500\P03052.jpg</path>
	<source>
		<database>Unknown</database>
	</source>
	<size>
		<width>660</width>
		<height>517</height>
		<depth>3</depth>
	</size>
	<segmented>0</segmented>
	<object>
		<name>gun</name>
		<pose>Unspecified</pose>
		<truncated>0</truncated>
		<difficult>0</difficult>
		<bndbox>
			<xmin>469</xmin>
			<ymin>246</ymin>
			<xmax>568</xmax>
			<ymax>424</ymax>
		</bndbox>
	</object>
	<object>
		<name>gun</name>
		<pose>Unspecified</pose>
		<truncated>0</truncated>
		<difficult>0</difficult>
		<bndbox>
			<xmin>476</xmin>
			<ymin>186</ymin>
			<xmax>590</xmax>
			<ymax>317</ymax>
		</bndbox>
	</object>
	<object>
		<name>knife</name>
		<pose>Unspecified</pose>
		<truncated>0</truncated>
		<difficult>0</difficult>
		<bndbox>
			<xmin>572</xmin>
			<ymin>79</ymin>
			<xmax>609</xmax>
			<ymax>435</ymax>
		</bndbox>
	</object>
</annotation>
