<annotation>
	<folder>Sixray annotation 500</folder>
	<filename>P04668.jpg</filename>
	<path>D:\Users\Joseph.ROSE-WS3A\Desktop\labelImg\data\Sixray annotation 500\P04668.jpg</path>
	<source>
		<database>Unknown</database>
	</source>
	<size>
		<width>690</width>
		<height>661</height>
		<depth>3</depth>
	</size>
	<segmented>0</segmented>
	<object>
		<name>plier</name>
		<pose>Unspecified</pose>
		<truncated>0</truncated>
		<difficult>0</difficult>
		<bndbox>
			<xmin>155</xmin>
			<ymin>276</ymin>
			<xmax>268</xmax>
			<ymax>440</ymax>
		</bndbox>
	</object>
	<object>
		<name>plier</name>
		<pose>Unspecified</pose>
		<truncated>0</truncated>
		<difficult>0</difficult>
		<bndbox>
			<xmin>253</xmin>
			<ymin>277</ymin>
			<xmax>294</xmax>
			<ymax>405</ymax>
		</bndbox>
	</object>
</annotation>
