<annotation>
	<folder>Sixray less than 500</folder>
	<filename>P05617.jpg</filename>
	<path>D:\Users\Joseph.ROSE-WS3A\Desktop\Sixray less than 500\P05617.jpg</path>
	<source>
		<database>Unknown</database>
	</source>
	<size>
		<width>462</width>
		<height>393</height>
		<depth>3</depth>
	</size>
	<segmented>0</segmented>
	<object>
		<name>scissor</name>
		<pose>Unspecified</pose>
		<truncated>0</truncated>
		<difficult>0</difficult>
		<bndbox>
			<xmin>74</xmin>
			<ymin>204</ymin>
			<xmax>180</xmax>
			<ymax>238</ymax>
		</bndbox>
	</object>
	<object>
		<name>plier</name>
		<pose>Unspecified</pose>
		<truncated>0</truncated>
		<difficult>0</difficult>
		<bndbox>
			<xmin>66</xmin>
			<ymin>182</ymin>
			<xmax>145</xmax>
			<ymax>217</ymax>
		</bndbox>
	</object>
</annotation>
