<annotation>
	<folder>Sixray less than 500</folder>
	<filename>P05990.jpg</filename>
	<path>D:\Users\Joseph.ROSE-WS3A\Desktop\Sixray less than 500\P05990.jpg</path>
	<source>
		<database>Unknown</database>
	</source>
	<size>
		<width>411</width>
		<height>640</height>
		<depth>3</depth>
	</size>
	<segmented>0</segmented>
	<object>
		<name>plier</name>
		<pose>Unspecified</pose>
		<truncated>0</truncated>
		<difficult>0</difficult>
		<bndbox>
			<xmin>180</xmin>
			<ymin>310</ymin>
			<xmax>284</xmax>
			<ymax>400</ymax>
		</bndbox>
	</object>
</annotation>
