<annotation>
	<folder>Sixray less than 500</folder>
	<filename>P06166.jpg</filename>
	<path>D:\Users\Joseph.ROSE-WS3A\Desktop\Sixray less than 500\P06166.jpg</path>
	<source>
		<database>Unknown</database>
	</source>
	<size>
		<width>374</width>
		<height>623</height>
		<depth>3</depth>
	</size>
	<segmented>0</segmented>
	<object>
		<name>wrench</name>
		<pose>Unspecified</pose>
		<truncated>0</truncated>
		<difficult>0</difficult>
		<bndbox>
			<xmin>283</xmin>
			<ymin>406</ymin>
			<xmax>338</xmax>
			<ymax>516</ymax>
		</bndbox>
	</object>
	<object>
		<name>plier</name>
		<pose>Unspecified</pose>
		<truncated>0</truncated>
		<difficult>0</difficult>
		<bndbox>
			<xmin>254</xmin>
			<ymin>365</ymin>
			<xmax>320</xmax>
			<ymax>451</ymax>
		</bndbox>
	</object>
</annotation>
