<annotation>
	<folder>Sixray less than 500</folder>
	<filename>P06304.jpg</filename>
	<path>D:\Users\Joseph.ROSE-WS3A\Desktop\Sixray less than 500\P06304.jpg</path>
	<source>
		<database>Unknown</database>
	</source>
	<size>
		<width>405</width>
		<height>474</height>
		<depth>3</depth>
	</size>
	<segmented>0</segmented>
	<object>
		<name>plier</name>
		<pose>Unspecified</pose>
		<truncated>0</truncated>
		<difficult>0</difficult>
		<bndbox>
			<xmin>56</xmin>
			<ymin>270</ymin>
			<xmax>131</xmax>
			<ymax>376</ymax>
		</bndbox>
	</object>
	<object>
		<name>wrench</name>
		<pose>Unspecified</pose>
		<truncated>0</truncated>
		<difficult>0</difficult>
		<bndbox>
			<xmin>64</xmin>
			<ymin>285</ymin>
			<xmax>139</xmax>
			<ymax>401</ymax>
		</bndbox>
	</object>
	<object>
		<name>wrench</name>
		<pose>Unspecified</pose>
		<truncated>0</truncated>
		<difficult>0</difficult>
		<bndbox>
			<xmin>47</xmin>
			<ymin>279</ymin>
			<xmax>125</xmax>
			<ymax>437</ymax>
		</bndbox>
	</object>
</annotation>
