<annotation>
	<folder>Sixray less than 500</folder>
	<filename>P06500.jpg</filename>
	<path>D:\Users\Joseph.ROSE-WS3A\Desktop\Sixray less than 500\P06500.jpg</path>
	<source>
		<database>Unknown</database>
	</source>
	<size>
		<width>480</width>
		<height>501</height>
		<depth>3</depth>
	</size>
	<segmented>0</segmented>
	<object>
		<name>plier</name>
		<pose>Unspecified</pose>
		<truncated>0</truncated>
		<difficult>0</difficult>
		<bndbox>
			<xmin>299</xmin>
			<ymin>134</ymin>
			<xmax>421</xmax>
			<ymax>171</ymax>
		</bndbox>
	</object>
	<object>
		<name>plier</name>
		<pose>Unspecified</pose>
		<truncated>0</truncated>
		<difficult>0</difficult>
		<bndbox>
			<xmin>260</xmin>
			<ymin>147</ymin>
			<xmax>435</xmax>
			<ymax>184</ymax>
		</bndbox>
	</object>
	<object>
		<name>plier</name>
		<pose>Unspecified</pose>
		<truncated>0</truncated>
		<difficult>0</difficult>
		<bndbox>
			<xmin>395</xmin>
			<ymin>337</ymin>
			<xmax>434</xmax>
			<ymax>432</ymax>
		</bndbox>
	</object>
</annotation>
