<annotation>
	<folder>Sixray annotation 500</folder>
	<filename>P07246.jpg</filename>
	<path>D:\Users\Joseph.ROSE-WS3A\Desktop\labelImg\data\Sixray annotation 500\P07246.jpg</path>
	<source>
		<database>Unknown</database>
	</source>
	<size>
		<width>642</width>
		<height>745</height>
		<depth>3</depth>
	</size>
	<segmented>0</segmented>
	<object>
		<name>wrench</name>
		<pose>Unspecified</pose>
		<truncated>0</truncated>
		<difficult>0</difficult>
		<bndbox>
			<xmin>130</xmin>
			<ymin>467</ymin>
			<xmax>203</xmax>
			<ymax>650</ymax>
		</bndbox>
	</object>
	<object>
		<name>plier</name>
		<pose>Unspecified</pose>
		<truncated>0</truncated>
		<difficult>0</difficult>
		<bndbox>
			<xmin>136</xmin>
			<ymin>558</ymin>
			<xmax>211</xmax>
			<ymax>662</ymax>
		</bndbox>
	</object>
</annotation>
