<annotation>
	<folder>Sixray less than 500</folder>
	<filename>P08468.jpg</filename>
	<path>D:\Users\Joseph.ROSE-WS3A\Desktop\Sixray less than 500\P08468.jpg</path>
	<source>
		<database>Unknown</database>
	</source>
	<size>
		<width>320</width>
		<height>436</height>
		<depth>3</depth>
	</size>
	<segmented>0</segmented>
	<object>
		<name>wrench</name>
		<pose>Unspecified</pose>
		<truncated>0</truncated>
		<difficult>0</difficult>
		<bndbox>
			<xmin>128</xmin>
			<ymin>93</ymin>
			<xmax>256</xmax>
			<ymax>401</ymax>
		</bndbox>
	</object>
</annotation>
