<annotation>
	<folder>Sixray annotation 500</folder>
	<filename>P08619.jpg</filename>
	<path>D:\Users\Joseph.ROSE-WS3A\Desktop\labelImg\data\Sixray annotation 500\P08619.jpg</path>
	<source>
		<database>Unknown</database>
	</source>
	<size>
		<width>720</width>
		<height>608</height>
		<depth>3</depth>
	</size>
	<segmented>0</segmented>
	<object>
		<name>plier</name>
		<pose>Unspecified</pose>
		<truncated>0</truncated>
		<difficult>0</difficult>
		<bndbox>
			<xmin>412</xmin>
			<ymin>74</ymin>
			<xmax>555</xmax>
			<ymax>115</ymax>
		</bndbox>
	</object>
	<object>
		<name>wrench</name>
		<pose>Unspecified</pose>
		<truncated>0</truncated>
		<difficult>0</difficult>
		<bndbox>
			<xmin>481</xmin>
			<ymin>147</ymin>
			<xmax>609</xmax>
			<ymax>177</ymax>
		</bndbox>
	</object>
	<object>
		<name>wrench</name>
		<pose>Unspecified</pose>
		<truncated>0</truncated>
		<difficult>0</difficult>
		<bndbox>
			<xmin>440</xmin>
			<ymin>161</ymin>
			<xmax>610</xmax>
			<ymax>185</ymax>
		</bndbox>
	</object>
</annotation>
