<annotation>
	<folder>Sixray annotation 500</folder>
	<filename>P08779.jpg</filename>
	<path>D:\Users\Joseph.ROSE-WS3A\Desktop\labelImg\data\Sixray annotation 500\P08779.jpg</path>
	<source>
		<database>Unknown</database>
	</source>
	<size>
		<width>534</width>
		<height>522</height>
		<depth>3</depth>
	</size>
	<segmented>0</segmented>
	<object>
		<name>plier</name>
		<pose>Unspecified</pose>
		<truncated>0</truncated>
		<difficult>0</difficult>
		<bndbox>
			<xmin>394</xmin>
			<ymin>225</ymin>
			<xmax>430</xmax>
			<ymax>364</ymax>
		</bndbox>
	</object>
	<object>
		<name>plier</name>
		<pose>Unspecified</pose>
		<truncated>0</truncated>
		<difficult>0</difficult>
		<bndbox>
			<xmin>342</xmin>
			<ymin>182</ymin>
			<xmax>380</xmax>
			<ymax>306</ymax>
		</bndbox>
	</object>
	<object>
		<name>plier</name>
		<pose>Unspecified</pose>
		<truncated>0</truncated>
		<difficult>0</difficult>
		<bndbox>
			<xmin>353</xmin>
			<ymin>225</ymin>
			<xmax>399</xmax>
			<ymax>333</ymax>
		</bndbox>
	</object>
	<object>
		<name>plier</name>
		<pose>Unspecified</pose>
		<truncated>0</truncated>
		<difficult>0</difficult>
		<bndbox>
			<xmin>356</xmin>
			<ymin>231</ymin>
			<xmax>405</xmax>
			<ymax>362</ymax>
		</bndbox>
	</object>
</annotation>
